mdump/__init__.py
mdump/cli.py
mdump/core.py
mdump-0.4.1.dist-info/METADATA
mdump-0.4.1.dist-info/WHEEL
mdump-0.4.1.dist-info/entry_points.txt
mdump-0.4.1.dist-info/licenses/LICENSE
mdump-0.4.1.dist-info/RECORD
