Metadata-Version: 2.4
Name: mdump
Version: 0.4.1
Summary: A tool to dump project structure and file contents to Markdown format
Author-email: ack2406 <ack9222@gmail.com>
License: MIT
License-File: LICENSE
Requires-Python: >=3.13
Requires-Dist: click>=8.0.0
Requires-Dist: gitpython>=3.1.0
Requires-Dist: pathspec>=0.9.0
Requires-Dist: pyperclip>=1.8.0
